handwriting/__init__.py
handwriting/admin.py
handwriting/forms.py
handwriting/static/handwriting/css/signpad.css
handwriting/static/handwriting/js/signpad.js
handwriting/templates/handwriting/handwriting.html
django_handwriting_widget-0.1.6.dist-info/METADATA
django_handwriting_widget-0.1.6.dist-info/WHEEL
django_handwriting_widget-0.1.6.dist-info/top_level.txt
django_handwriting_widget-0.1.6.dist-info/RECORD
