Metadata-Version: 2.1
Name: django-handwriting-widget
Version: 0.1.6
Summary: A handwriting widget for django
Home-page: https://github.com/arthurc0102/django-handwriting-widget
Author: Arthur Chang
Author-email: arthurc0102@gmail.com
License: UNKNOWN
Keywords: handwrite
Platform: UNKNOWN
Classifier: Programming Language :: Python :: 3
Requires-Dist: django
